other_gates/gdmux8way16/gdmux8way16.v
module gdmux8way16 (
    input [15:0] d,
    input [2:0] sel,
    output [15:0] y0,
    output [15:0] y1,
    output [15:0] y2,
    output [15:0] y3,
    output [15:0] y4,
    output [15:0] y5,
    output [15:0] y6,
    output [15:0] y7
);
    assign y0 = (sel == 3'b000) ? d : 16'b0;
    assign y1 = (sel == 3'b001) ? d : 16'b0;
    assign y2 = (sel == 3'b010) ? d : 16'b0;
    assign y3 = (sel == 3'b011) ? d : 16'b0;
    assign y4 = (sel == 3'b100) ? d : 16'b0;
    assign y5 = (sel == 3'b101) ? d : 16'b0;
    assign y6 = (sel == 3'b110) ? d : 16'b0;
    assign y7 = (sel == 3'b111) ? d : 16'b0;
    
endmodule

other_gates/gdmux8way16/tb_gdmux8way16.v
`include "gdmux8way16.v"

module tb_gdmux8way16;
    reg [15:0] d;
    reg [2:0] sel;
    wire [15:0] y0, y1, y2, y3, y4, y5, y6, y7;

    gdmux8way16 uut (
        .d(d),
        .sel(sel),
        .y0(y0),
        .y1(y1),
        .y2(y2),
        .y3(y3),
        .y4(y4),
        .y5(y5),
        .y6(y6),
        .y7(y7)
    );

    initial begin
        $display("Gdmux8way16 Testbench");
        $dumpfile("signals.vcd");
        $dumpvars(0, tb_gdmux8way16);

        d = 16'hA5A5; sel = 3'b000; #10;
        d = 16'h5A5A; sel = 3'b001; #10;
        d = 16'hFFFF; sel = 3'b010; #10;
        d = 16'h0000; sel = 3'b011; #10;
        d = 16'h1234; sel = 3'b100; #10;
        d = 16'h5678; sel = 3'b101; #10;
        d = 16'h9ABC; sel = 3'b110; #10;
        d = 16'hDEF0; sel = 3'b111; #10;

        $finish;
    end

    initial begin
        $monitor("Time: %0t | Sel: %b | D: %h | Y0: %h | Y1: %h | Y2: %h | Y3: %h | Y4: %h | Y5: %h | Y6: %h | Y7: %h", 
                 $time, sel, d, y0, y1, y2, y3, y4, y5, y6, y7);
    end

endmodule

other_gates/gdmux8way16/signals.vcd
$date
	Fri Mar 21 16:15:26 2025
$end
$version
	Icarus Verilog
$end
$timescale
	1s
$end
$scope module tb_gdmux8way16 $end
$var wire 16 ! y7 [15:0] $end
$var wire 16 " y6 [15:0] $end
$var wire 16 # y5 [15:0] $end
$var wire 16 $ y4 [15:0] $end
$var wire 16 % y3 [15:0] $end
$var wire 16 & y2 [15:0] $end
$var wire 16 ' y1 [15:0] $end
$var wire 16 ( y0 [15:0] $end
$var reg 16 ) d [15:0] $end
$var reg 3 * sel [2:0] $end
$scope module uut $end
$var wire 16 + d [15:0] $end
$var wire 3 , sel [2:0] $end
$var wire 16 - y7 [15:0] $end
$var wire 16 . y6 [15:0] $end
$var wire 16 / y5 [15:0] $end
$var wire 16 0 y4 [15:0] $end
$var wire 16 1 y3 [15:0] $end
$var wire 16 2 y2 [15:0] $end
$var wire 16 3 y1 [15:0] $end
$var wire 16 4 y0 [15:0] $end
$upscope $end
$upscope $end
$enddefinitions $end
$comment Show the parameter values. $end
$dumpall
$end
#0
$dumpvars
b1010010110100101 4
b0 3
b0 2
b0 1
b0 0
b0 /
b0 .
b0 -
b0 ,
b1010010110100101 +
b0 *
b1010010110100101 )
b1010010110100101 (
b0 '
b0 &
b0 %
b0 $
b0 #
b0 "
b0 !
$end
#10
b101101001011010 '
b101101001011010 3
b0 (
b0 4
b1 *
b1 ,
b101101001011010 )
b101101001011010 +
#20
b1111111111111111 &
b1111111111111111 2
b0 '
b0 3
b10 *
b10 ,
b1111111111111111 )
b1111111111111111 +
#30
b0 &
b0 2
b11 *
b11 ,
b0 )
b0 +
#40
b1001000110100 $
b1001000110100 0
b100 *
b100 ,
b1001000110100 )
b1001000110100 +
#50
b101011001111000 #
b101011001111000 /
b0 $
b0 0
b101 *
b101 ,
b101011001111000 )
b101011001111000 +
#60
b1001101010111100 "
b1001101010111100 .
b0 #
b0 /
b110 *
b110 ,
b1001101010111100 )
b1001101010111100 +
#70
b1101111011110000 !
b1101111011110000 -
b0 "
b0 .
b111 *
b111 ,
b1101111011110000 )
b1101111011110000 +
